.gitignore
LICENSE
README.md
api_docs.md
setup.py
configs/bellande/http_configs.bellande
configs/bellande/tcp_configs.bellande
configs/bellande/tls_configs.bellande
configs/json/http_configs.json
configs/json/tcp_configs.json
configs/json/tls_configs.json
graphs_charts/graph_charts_1/10D_Space.png
graphs_charts/graph_charts_1/2D_Space.png
graphs_charts/graph_charts_1/3D_Space.png
graphs_charts/graph_charts_1/4D_Space.png
graphs_charts/graph_charts_1/5D_Space.png
graphs_charts/graph_charts_1/6D_Space.png
graphs_charts/graph_charts_1/7D_Space.png
graphs_charts/graph_charts_1/8D_Space.png
graphs_charts/graph_charts_1/9D_Space.png
graphs_charts/graph_charts_100/10D_Space.png
graphs_charts/graph_charts_100/2D_Space.png
graphs_charts/graph_charts_100/3D_Space.png
graphs_charts/graph_charts_100/4D_Space.png
graphs_charts/graph_charts_100/5D_Space.png
graphs_charts/graph_charts_100/6D_Space.png
graphs_charts/graph_charts_100/7D_Space.png
graphs_charts/graph_charts_100/8D_Space.png
graphs_charts/graph_charts_100/9D_Space.png
graphs_charts/graph_charts_25/10D_Space.png
graphs_charts/graph_charts_25/2D_Space.png
graphs_charts/graph_charts_25/3D_Space.png
graphs_charts/graph_charts_25/4D_Space.png
graphs_charts/graph_charts_25/5D_Space.png
graphs_charts/graph_charts_25/6D_Space.png
graphs_charts/graph_charts_25/7D_Space.png
graphs_charts/graph_charts_25/8D_Space.png
graphs_charts/graph_charts_25/9D_Space.png
graphs_charts/graph_charts_50/10D_Space.png
graphs_charts/graph_charts_50/2D_Space.png
graphs_charts/graph_charts_50/3D_Space.png
graphs_charts/graph_charts_50/4D_Space.png
graphs_charts/graph_charts_50/5D_Space.png
graphs_charts/graph_charts_50/6D_Space.png
graphs_charts/graph_charts_50/7D_Space.png
graphs_charts/graph_charts_50/8D_Space.png
graphs_charts/graph_charts_50/9D_Space.png
graphs_charts/graph_charts_75/10D_Space.png
graphs_charts/graph_charts_75/2D_Space.png
graphs_charts/graph_charts_75/3D_Space.png
graphs_charts/graph_charts_75/4D_Space.png
src/bellande_robot_step.egg-info/PKG-INFO
src/bellande_robot_step.egg-info/SOURCES.txt
src/bellande_robot_step.egg-info/dependency_links.txt
src/bellande_robot_step.egg-info/entry_points.txt
src/bellande_robot_step.egg-info/requires.txt
src/bellande_robot_step.egg-info/top_level.txt
