Metadata-Version: 2.1
Name: bellande-robot-step
Version: 0.3.3
Summary: Robots Step
Home-page: UNKNOWN
Author: RonaldsonBellande
Author-email: ronaldsonbellande@gmail.com
License: UNKNOWN
Project-URL: Home, https://github.com/RonaldsonBellande/bellande_step
Project-URL: Homepage, https://github.com/RonaldsonBellande/bellande_step
Project-URL: documentation, https://github.com/RonaldsonBellande/bellande_step
Project-URL: repository, https://github.com/RonaldsonBellande/bellande_step
Keywords: package,setuptools
Platform: UNKNOWN
Classifier: License :: OSI Approved :: GNU General Public License v3 (GPLv3)
Classifier: Programming Language :: Python
Requires-Python: >=3.0
Provides-Extra: dev
